__reloader__.py
reloader.py
reloader_py-0.18.0.dist-info/METADATA
reloader_py-0.18.0.dist-info/WHEEL
reloader_py-0.18.0.dist-info/entry_points.txt
reloader_py-0.18.0.dist-info/licenses/LICENSE
reloader_py-0.18.0.dist-info/RECORD
